rice/__init__.py
rice/serializer.py
rice-0.4.dist-info/LICENSE
rice-0.4.dist-info/METADATA
rice-0.4.dist-info/WHEEL
rice-0.4.dist-info/top_level.txt
rice-0.4.dist-info/RECORD
