Metadata-Version: 2.1
Name: rice
Version: 0.4
Summary: Non intrusive serialization library
Home-page: https://github.com/bmat/rice
Author: BMAT developers
Author-email: tv-av@bmat.com
License: UNKNOWN
Download-URL: https://github.com/bmat/rice/archive/master.zip
Keywords: rice,serialization,deserialization,doc
Platform: UNKNOWN
Classifier: Topic :: Adaptive Technologies
Classifier: Topic :: Software Development
Classifier: Topic :: System
Classifier: Topic :: Utilities
Requires-Dist: docutils (==0.14)
Requires-Dist: marshmallow (==2.15.3)
Requires-Dist: marshmallow-enum (==1.4.1)
